ConsoleFun/__init__.py
ConsoleFun/guessing_game.py
ConsoleFun/list_games.py
ConsoleFun/rps.py
ConsoleFun-0.1.2.dist-info/METADATA
ConsoleFun-0.1.2.dist-info/WHEEL
ConsoleFun-0.1.2.dist-info/entry_points.txt
ConsoleFun-0.1.2.dist-info/top_level.txt
ConsoleFun-0.1.2.dist-info/RECORD
