Metadata-Version: 2.1
Name: ConsoleFun
Version: 0.1.2
Summary: Developed primarily for fun and learning purposes, this collection serves as a playground for budding developers and gamers alike. As such, you might encounter a few bugs along the way—consider them part of the adventure!
Home-page: https://github.com/memanja/ConsoleGames
Author: Manoj Shetty K
Author-email: shettykmanojmask@gmail.com
Classifier: Programming Language :: Python :: 3
Classifier: License :: OSI Approved :: MIT License
Classifier: Operating System :: OS Independent
Requires-Python: >=3.6
Requires-Dist: pyfiglet
Requires-Dist: prettytable
Requires-Dist: colorama
